places_client/__init__.py
places_client/places_client.py
places_client-0.3.0.dist-info/LICENSE
places_client-0.3.0.dist-info/METADATA
places_client-0.3.0.dist-info/WHEEL
places_client-0.3.0.dist-info/RECORD
