Metadata-Version: 2.3
Name: places_client
Version: 0.3.0
Summary: Python package for extracting health outcomes and health-risk behaviors data from CDC PLACES API
License: MIT
Author: Yixiao Liu
Requires-Python: >=3.12
Classifier: License :: OSI Approved :: MIT License
Classifier: Programming Language :: Python :: 3
Classifier: Programming Language :: Python :: 3.12
Classifier: Programming Language :: Python :: 3.13
Provides-Extra: dev
Requires-Dist: mypy (>=1.19.0) ; extra == "dev"
Requires-Dist: myst-nb (>=1.3.0) ; extra == "dev"
Requires-Dist: pandas (>=2.3.3)
Requires-Dist: pytest (>=9.0.2) ; extra == "dev"
Requires-Dist: pytest-cov (>=7.0.0) ; extra == "dev"
Requires-Dist: pytest-mock (>=3.15.1) ; extra == "dev"
Requires-Dist: requests (>=2.32.5)
Requires-Dist: sphinx-autoapi (>=3.6.1) ; extra == "dev"
Requires-Dist: sphinx-rtd-theme (>=3.0.2) ; extra == "dev"
